k3sconfig/__init__.py
k3sconfig/app.py
k3sconfig-0.1.0.dist-info/entry_points.txt
k3sconfig-0.1.0.dist-info/WHEEL
k3sconfig-0.1.0.dist-info/METADATA
k3sconfig-0.1.0.dist-info/RECORD
