Metadata-Version: 2.1
Name: k3sconfig
Version: 0.1.0
Summary: 
Author: Anatoly Gusev
Author-email: gusev.tolia@yandex.ru
Requires-Python: >=3.9,<4.0
Classifier: Programming Language :: Python :: 3
Classifier: Programming Language :: Python :: 3.9
Requires-Dist: PyYAML (>=6.0,<7.0)
Requires-Dist: click (>=8.0.4,<9.0.0)
Requires-Dist: fastapi (>=0.75.1,<0.76.0)
Requires-Dist: requests (>=2.27.1,<3.0.0)
Requires-Dist: uvicorn[standard] (>=0.17.6,<0.18.0)
